{
  "hash": "30dcf70d",
  "browserHash": "b3522163",
  "optimized": {
    "vue": {
      "src": "../../../../node_modules/vue/dist/vue.runtime.esm-bundler.js",
      "file": "vue.js",
      "fileHash": "0c21ed77",
      "needsInterop": false
    },
    "md5": {
      "src": "../../../../node_modules/md5/md5.js",
      "file": "md5.js",
      "fileHash": "a3cfaebb",
      "needsInterop": true
    },
    "gitalk": {
      "src": "../../../../node_modules/gitalk/dist/gitalk.js",
      "file": "gitalk.js",
      "fileHash": "d3ff2695",
      "needsInterop": true
    }
  },
  "chunks": {
    "chunk-RSJERJUL": {
      "file": "chunk-RSJERJUL.js"
    }
  }
}